etesync_dav/__init__.py
etesync_dav/config.py
etesync_dav-0.1.7.data/scripts/etesync-dav
etesync_dav-0.1.7.data/scripts/etesync-dav-manage
etesync_dav-0.1.7.dist-info/METADATA
etesync_dav-0.1.7.dist-info/RECORD
etesync_dav-0.1.7.dist-info/WHEEL
etesync_dav-0.1.7.dist-info/top_level.txt
