Metadata-Version: 2.1
Name: etesync-dav
Version: 0.1.7
Summary: A CalDAV and CardDAV frontend for EteSync
Home-page: https://github.com/etesync/etesync-dav
Author: EteSync
Author-email: development@etesync.com
License: GPL
Keywords: etesync,encryption,sync,pim,caldav,carddav
Platform: UNKNOWN
Requires-Dist: appdirs (>=1.4.3)
Requires-Dist: radicale-storage-etesync (>=0.1.7)
